app/__init__.py
app/cmd_colors.py
app/prypip.py
app/openl/__init__.py
app/openl/depen_tree.py
app/openl/main.py
app/run/__init__.py
app/run/install.py
app/run/main.py
app/run/uninstall.py
app/run/upgrade.py
app/run/utils.py
prypip-1.0.8.dist-info/LICENSE
prypip-1.0.8.dist-info/METADATA
prypip-1.0.8.dist-info/WHEEL
prypip-1.0.8.dist-info/entry_points.txt
prypip-1.0.8.dist-info/top_level.txt
prypip-1.0.8.dist-info/RECORD
