Metadata-Version: 2.1
Name: prypip
Version: 1.0.8
Summary: pip for wrapper for properly auto updating requirements.txt and sorting out dependencies
Home-page: https://www.github.com/precious112/prypip
Author: Balogun Precious
Author-email: preciouskent8@gmail.com
License: UNKNOWN
Keywords: pip,requirements,requirements.txt,dependency management
Platform: UNKNOWN
Requires-Python: >=3.8
Requires-Dist: colorama
